HISTORY.rst
LICENSE
MANIFEST.in
Makefile
README.rst
requirements.txt
requirements_dev.txt
requirements_rtfd.txt
setup.py
cyl1tf/__init__.py
cyl1tf/interface.pyx
cyl1tf.egg-info/PKG-INFO
cyl1tf.egg-info/SOURCES.txt
cyl1tf.egg-info/dependency_links.txt
cyl1tf.egg-info/not-zip-safe
cyl1tf.egg-info/top_level.txt
source/COPYING.TXT
source/Makefile
source/README.TXT
source/blas.h
source/l1tf.c
source/l1tf.h
source/lapack.h
tests/test_example.py
tests/test_interface.py
tests/data/results-r0_01.txt
tests/data/results-s50.txt
tests/data/snp500.txt