Metadata-Version: 2.1
Name: cyl1tf
Version: 0.1.3
Summary: Cython implementation of L1 trend fitting.
Home-page: https://github.com/arkottke/cyl1tf
Author: Albert Kottke
Author-email: albert.kottke@gmail.com
License: UNKNOWN
Platform: UNKNOWN
License-File: LICENSE
